{"1045":{"category":4.0,"name":"AA MCrMo2","Applications":"Construction of containers, boilers, machines and pipe work. Steam boilers and turbines construction.","As":null,"C":0.07,"Cr":2.3,"Cu":0.0,"Diffusible Hydrogen":null,"Mn":1.0,"Mn + Ni + Cr + Mo + V":null,"Mo":1.1,"N":0.0,"Nb":0.0,"Ni":0.0,"Ni+Mn":null,"P":0.015,"P S":null,"S":0.015,"S Ni":null,"SN":null,"Si":0.3,"Si P":null,"Sn":0.0,"Suitable_For":"\n\nMaterialsBoiler steels--\nDIN10CrMo9-1010CrSiMoV712CrMo9-10\nEN10CrMo9-1012CrMo9-10-\nASTMtypicalA 387 Gr. 22-\n\n","V":0.0,"conformances":null,"ind":null,"url":"http:\/\/www.ceweld.nl\/en\/product\/aa-mcrmo2"}}