{"1206":{"category":2.0,"name":"312 Tig","Applications":"Buffer layers before hardfacing, armor plate, exhaust systems, high, Manganese austenitic steel, heterogeneous welding, difficult to weld and unknown steels.","As":null,"C":0.15,"Cr":30.0,"Cu":0.75,"Diffusible Hydrogen":null,"Mn":1.75,"Mn + Ni + Cr + Mo + V":null,"Mo":0.75,"N":0.0,"Nb":0.0,"Ni":9.25,"Ni+Mn":null,"P":0.03,"P S":null,"S":0.03,"S Ni":null,"SN":null,"Si":0.475,"Si P":null,"Sn":0.0,"Suitable_For":"Buffer layers, armor plate,\u00a0409, 304,\u00a0difficult to weld steels such as:, 25CrMo4, 42CrMo4, 50CrMo4,\u00a042MnV7, 1.7218, 1.7225, 1.7228, 1.7223, AISI: 4130, 4140, 4150, C45, C60, tool steel repairs etc..","V":0.0,"conformances":null,"ind":null,"url":"http:\/\/www.ceweld.nl\/en\/product\/312-tig"}}