{"1230":{"category":2.0,"name":"ER 110 S-G Tig","Applications":"Crane building, heavy constructions, lifting, offshore platforms, transport etc.","As":null,"C":0.07,"Cr":0.3,"Cu":0.0,"Diffusible Hydrogen":null,"Mn":1.6,"Mn + Ni + Cr + Mo + V":null,"Mo":0.4,"N":0.0,"Nb":0.0,"Ni":2.1,"Ni+Mn":null,"P":0.0,"P S":null,"S":0.0,"S Ni":null,"SN":null,"Si":0.45,"Si P":null,"Sn":0.0,"Suitable_For":"S690QL, Dillidur 690, Weldox 700, Naxtra 70, S700MC, Alform 700 M, Domex 700 MC, PAS 70, S770QL","V":0.0,"conformances":null,"ind":null,"url":"http:\/\/www.ceweld.nl\/en\/product\/er-110-s-g-tig"}}