{"1361":{"category":2.0,"name":"327","Applications":"Cap layers for joining refractory Cr-Al-Si steels, cladding corrosion resistant overlays, cladding heat resistant overlays up to 1100\u00baC, cladding components in a sulphurous environment.","As":null,"C":0.1,"Cr":25.5,"Cu":0.0,"Diffusible Hydrogen":null,"Mn":1.75,"Mn + Ni + Cr + Mo + V":null,"Mo":0.0,"N":0.0,"Nb":0.0,"Ni":5.0,"Ni+Mn":null,"P":0.0,"P S":null,"S":0.0,"S Ni":null,"SN":null,"Si":0.6,"Si P":null,"Sn":0.0,"Suitable_For":"\n\nW.Nr:1.47101.47451.47121.47621.47131.47731.47221.4776\n\nEN ASTM\/ACIG-X30CrSi6G-X40CrSi23 TP433X10CrSi6 502X10CrAl24 TP443X10CrAl7 502X8Cr30X10CrSi13G-X40CrSi29\n\nW.Nr:1.47241.48201.47291.48211.47401.48221.47421.4823\n\nEN ASTM\/ACIX10CrAl13 TP405-CA15G-X12 CrSi 26 5G-X40CrSi13X20 CrNiSi 25 4 TP329G-X40CrSi17G-X40CrNi 25 4 TP329X10CrAl18 430B-TP430G-X40CrNiSi 27 4 TP329HC\n\n\n\n\u00a0","V":0.0,"conformances":null,"ind":null,"url":"http:\/\/www.ceweld.nl\/en\/product\/327"}}