{"597":{"category":"aluminum-mig-tig","name":"Products_Consumable_StickElectrodes-MildandLowAlloySteels-Pipeliner-Pipeliner7PPlus(LincolnElectric)","Applications":"diameters-\/-packaging","As":null,"C":0.155,"Cr":0.035,"Cu":null,"Diffusible Hydrogen":null,"Mn":0.67,"Mn + Ni + Cr + Mo + V":null,"Mo":0.565,"N":null,"Nb":null,"Ni":0.715,"Ni+Mn":null,"P":0.015,"P S":null,"S":null,"S Ni":null,"SN":null,"Si":0.15,"Si P":null,"Sn":null,"Suitable_For":"conformances\naws-a5.5\/a5.5m:-2006-e9010-g\nasme-sfa-a5.5:-e9010-g\nwelding-positions\nall","V":null,"conformances":"key-features\n(cid:23)(cid:3)light-slag-for-mal-arc-interference-\n(cid:23)(cid:3)deep-penetration-\n(cid:23)(cid:3)clean,-visible-weld-puddle-\n(cid:23)(cid:3)superior-puddle-control","ind":339.0,"url":"https:\/\/www.lincolnelectric.com\/en-us\/Consumables\/Pages\/product.aspx?product=Products_Consumable_StickElectrodes-MildandLowAlloySteels-Pipeliner-Pipeliner7PPlus(LincolnElectric)"}}