{"998":{"category":4.0,"name":"AA 309LP","Applications":"Ceweld AA 309LP is used for welding dissimilar steels and 13%Cr\/18%Cr stainless steels, and is suitable for welding the first layer on low carbon steel to obtain a AISI 304 clad layer.","As":null,"C":0.03,"Cr":23.5,"Cu":0.0,"Diffusible Hydrogen":null,"Mn":1.3,"Mn + Ni + Cr + Mo + V":null,"Mo":0.1,"N":0.0,"Nb":0.0,"Ni":12.5,"Ni+Mn":null,"P":0.0018,"P S":null,"S":0.005,"S Ni":null,"SN":null,"Si":0.7,"Si P":null,"Sn":0.0,"Suitable_For":"Buffer layers before hard facing, dissimilar joints between ferritic and austenitic steels and or difficult to weld steels such as: 42CrMo4, C45, 42MnV7, tool steels, heat resistant steels\u00a0etc.\n\u00a0","V":0.0,"conformances":null,"ind":null,"url":"http:\/\/www.ceweld.nl\/en\/product\/aa-309lp"}}